projectreadmegenerator/__init__.py
projectreadmegenerator/customuserinput.py
projectreadmegenerator/generator.py
projectreadmegenerator/storage.py
projectreadme-0.2.1.dist-info/METADATA
projectreadme-0.2.1.dist-info/WHEEL
projectreadme-0.2.1.dist-info/entry_points.txt
projectreadme-0.2.1.dist-info/top_level.txt
projectreadme-0.2.1.dist-info/RECORD
